pylertatron/Pylertatron.py
pylertatron/__init__.py
pylertatron/commands.py
pylertatron/async_/__init__.py
pylertatron/async_/pylertatron.py
pylertatron/sync/__init__.py
pylertatron/sync/pylertatron.py
pylertatron-1.0.5.dist-info/LICENSE
pylertatron-1.0.5.dist-info/WHEEL
pylertatron-1.0.5.dist-info/METADATA
pylertatron-1.0.5.dist-info/RECORD
